{
  "scopes":[
    {
      "key":"read:submission-tracker",
      "name":"Execute submission-tracker call",
      "description":"Retrieve tracking data"
    }
  ],
  "api":{
    "name":"submission-tracker",
    "description":"The API is used to retrieve tracking information.",
    "context":"submission-tracker",
    "versions":[
      {
        "version":"1.0",
        "status":"PROTOTYPED",
        "endpoints":[
          {
            "uriPattern":"/tracking/:id/:idType",
            "endpointName":"Tracking-Data",
            "method":"GET",
            "authType":"USER",
            "throttlingTier":"UNLIMITED",
            "scope":"read:submission-tracker"
          }
        ]
      }
    ]
  }
}
